pdfhstack.py
pdfhstack-0.1.0.dist-info/METADATA
pdfhstack-0.1.0.dist-info/WHEEL
pdfhstack-0.1.0.dist-info/entry_points.txt
pdfhstack-0.1.0.dist-info/top_level.txt
pdfhstack-0.1.0.dist-info/RECORD
